JadeGeometry/__init__.py
JadeGeometry/math.py
JadeGeometry/random.py
JadeGeometry/surfarea.py
JadeGeometry/volume.py
JadeGeometry-1.0.10.dist-info/LICENSE
JadeGeometry-1.0.10.dist-info/METADATA
JadeGeometry-1.0.10.dist-info/WHEEL
JadeGeometry-1.0.10.dist-info/top_level.txt
JadeGeometry-1.0.10.dist-info/RECORD
